simplediskimage/__init__.py
simplediskimage/cfr.py
simplediskimage/common.py
simplediskimage/partitioners.py
simplediskimage/tools.py
simplediskimage-0.3.dist-info/LICENSE
simplediskimage-0.3.dist-info/METADATA
simplediskimage-0.3.dist-info/WHEEL
simplediskimage-0.3.dist-info/top_level.txt
simplediskimage-0.3.dist-info/RECORD
