Metadata-Version: 2.1
Name: simplediskimage
Version: 0.3
Summary: Library used to build simple disk images with multiple partitions
Home-page: https://github.com/zqad/simplediskimage/
Author: Jonas Eriksson
Author-email: jonas@upto.se
License: Apache-2.0
Project-URL: Documentation, https://simplediskimage.readthedocs.io/
Platform: UNKNOWN
Classifier: Programming Language :: Python :: 3
Classifier: License :: OSI Approved :: Apache Software License
Classifier: Operating System :: OS Independent
Requires-Python: >=3.4
Requires-Dist: pyparted
